fastapi_structured_logging.py
fastapi_structured_logging-1.0.1.dist-info/licenses/LICENSE
fastapi_structured_logging-1.0.1.dist-info/METADATA
fastapi_structured_logging-1.0.1.dist-info/WHEEL
fastapi_structured_logging-1.0.1.dist-info/top_level.txt
fastapi_structured_logging-1.0.1.dist-info/RECORD
